{
	"name": "DS_JSON_SINK",
	"properties": {
		"linkedServiceName": {
			"referenceName": "LS_JSON_SINK",
			"type": "LinkedServiceReference"
		},
		"annotations": [],
		"type": "Parquet",
		"typeProperties": {
			"location": {
				"type": "AzureBlobFSLocation",
				"folderPath": {
					"value": "@concat('json/',formatDateTime(utcNow(),'yyyy'),'/',formatDateTime(utcNow(),'MM'),'/',formatDateTime(utcNow(),'dd'))",
					"type": "Expression"
				},
				"fileSystem": "input"
			},
			"compressionCodec": "snappy"
		},
		"schema": [
			{
				"name": "geolocation_zip_code_prefix",
				"type": "UTF8"
			},
			{
				"name": "geolocation_lat",
				"type": "UTF8"
			},
			{
				"name": "geolocation_lng",
				"type": "UTF8"
			},
			{
				"name": "geolocation_city",
				"type": "UTF8"
			},
			{
				"name": "geolocation_state",
				"type": "UTF8"
			}
		]
	},
	"type": "Microsoft.DataFactory/factories/datasets"
}