{
	"name": "DS_SQLSERVER_PARQ_SINK",
	"properties": {
		"linkedServiceName": {
			"referenceName": "LS_SQLSERVER_PARQ_SINK",
			"type": "LinkedServiceReference"
		},
		"annotations": [],
		"type": "Parquet",
		"typeProperties": {
			"location": {
				"type": "AzureBlobFSLocation",
				"folderPath": {
					"value": "@concat('sqlserver/',formatDateTime(utcNow(),'yyyy'),'/',formatDateTime(utcNow(),'MM'),'/',formatDateTime(utcNow(),'dd'))",
					"type": "Expression"
				},
				"fileSystem": "input"
			},
			"compressionCodec": "snappy"
		},
		"schema": []
	},
	"type": "Microsoft.DataFactory/factories/datasets"
}